unityrde/__init__.py
unityrde/tests.py
unityrde/unity_raw_data_export.py
unityrde-0.0.6.dist-info/LICENSE
unityrde-0.0.6.dist-info/METADATA
unityrde-0.0.6.dist-info/WHEEL
unityrde-0.0.6.dist-info/top_level.txt
unityrde-0.0.6.dist-info/RECORD
