Metadata-Version: 2.1
Name: unityrde
Version: 0.0.6
Summary: A Python package for the Unity Analytics Raw Data Export REST API
Home-page: https://github.com/bwildi/unityrde/tree/master/unityrde
Author: Billy Wildi
Author-email: bwildi94@gmail.com
License: UNKNOWN
Platform: UNKNOWN
Classifier: Programming Language :: Python :: 3
Classifier: License :: OSI Approved :: MIT License
Classifier: Operating System :: OS Independent
Requires-Python: >=3.5
